setup.py
docs/HISTORY.txt
docs/INSTALL.txt
docs/LICENSE.GPL
docs/LICENSE.txt
docs/README.txt
docs/TODO.txt
vice/__init__.py
vice.outbound.egg-info/PKG-INFO
vice.outbound.egg-info/SOURCES.txt
vice.outbound.egg-info/dependency_links.txt
vice.outbound.egg-info/entry_points.txt
vice.outbound.egg-info/namespace_packages.txt
vice.outbound.egg-info/not-zip-safe
vice.outbound.egg-info/requires.txt
vice.outbound.egg-info/top_level.txt
vice/outbound/README.txt
vice/outbound/TODO.txt
vice/outbound/__init__.py
vice/outbound/config.py
vice/outbound/configure.zcml
vice/outbound/feedconfig.py
vice/outbound/feedsettings.py
vice/outbound/ftesting.zcml
vice/outbound/interfaces.py
vice/outbound/permissions.zcml
vice/outbound/adapters/__init__.py
vice/outbound/adapters/configure.zcml
vice/outbound/browser/__init__.py
vice/outbound/browser/atom-1.0.pt
vice/outbound/browser/configure.zcml
vice/outbound/browser/feed-icon-14x14.png
vice/outbound/browser/feed-icon-28x28.png
vice/outbound/browser/feed-icon-atom-80x15.gif
vice/outbound/browser/feed-icon-rdf-80x15.gif
vice/outbound/browser/feed-icon-rss-80x15.gif
vice/outbound/browser/feed.py
vice/outbound/browser/feed_config.pt
vice/outbound/browser/feed_config_grid.pt
vice/outbound/browser/feedconfig.py
vice/outbound/browser/rss-1.0.pt
vice/outbound/browser/rss-2.0.pt
vice/outbound/browser/widgets.py
vice/outbound/feedformats/__init__.py
vice/outbound/feedformats/configure.zcml
vice/outbound/feedformats/feedformats.py
vice/outbound/feedformats/interfaces.py
vice/outbound/ftests/__init__.py
vice/outbound/ftests/setup.py
vice/outbound/tests/__init__.py
vice/outbound/tests/basefunctional.py
vice/outbound/tests/enclosure.txt
vice/outbound/tests/test.py
vice/outbound/tests/testUnit.py
vice/outbound/tests/unTestFunctional.py